{
  "m_GameObject": {
    "m_FileID": 0,
    "m_PathID": 3146412515404193728
  },
  "m_Enabled": 1,
  "m_Script": {
    "m_FileID": 0,
    "m_PathID": 6110361863302487732
  },
  "m_Name": "",
  "hints": [
    {
      "m_FileID": 0,
      "m_PathID": -5596435521163606874
    },
    {
      "m_FileID": 0,
      "m_PathID": 9076074368357910837
    },
    {
      "m_FileID": 0,
      "m_PathID": -3642926043456874972
    },
    {
      "m_FileID": 0,
      "m_PathID": 3169134650530651182
    },
    {
      "m_FileID": 0,
      "m_PathID": -9192843104600516563
    }
  ]
}