{
  "m_GameObject": {
    "m_FileID": 0,
    "m_PathID": -2630544814986193467
  },
  "m_Enabled": 1,
  "m_Script": {
    "m_FileID": 0,
    "m_PathID": 4670242947070272867
  },
  "m_Name": "",
  "_userData": {
    "_allowedNpadStyles": -1,
    "_joyConGripStyle": 1,
    "_adjustIMUsForGripStyle": 1,
    "_handheldActivationMode": 0,
    "_assignJoysticksByNpadId": 1,
    "_useVibrationThread": 1,
    "_npadNo1": {
      "_isAllowed": 1,
      "_rewiredPlayerId": 0,
      "_joyConAssignmentMode": 1
    },
    "_npadNo2": {
      "_isAllowed": 1,
      "_rewiredPlayerId": 1,
      "_joyConAssignmentMode": 1
    },
    "_npadNo3": {
      "_isAllowed": 1,
      "_rewiredPlayerId": 2,
      "_joyConAssignmentMode": 1
    },
    "_npadNo4": {
      "_isAllowed": 1,
      "_rewiredPlayerId": 3,
      "_joyConAssignmentMode": 1
    },
    "_npadNo5": {
      "_isAllowed": 0,
      "_rewiredPlayerId": 4,
      "_joyConAssignmentMode": -1
    },
    "_npadNo6": {
      "_isAllowed": 0,
      "_rewiredPlayerId": 5,
      "_joyConAssignmentMode": -1
    },
    "_npadNo7": {
      "_isAllowed": 0,
      "_rewiredPlayerId": 6,
      "_joyConAssignmentMode": -1
    },
    "_npadNo8": {
      "_isAllowed": 0,
      "_rewiredPlayerId": 7,
      "_joyConAssignmentMode": -1
    },
    "_npadHandheld": {
      "_isAllowed": 1,
      "_rewiredPlayerId": 0,
      "_joyConAssignmentMode": -1
    },
    "_debugPad": {
      "_enabled": 0,
      "_rewiredPlayerId": 0
    }
  }
}